loadingpy/__init__.py
loadingpy/alias.py
loadingpy/basic_bar.py
loadingpy/colored_bar.py
loadingpy/loading_bar.py
loadingpy/py.typed
loadingpy/training_bar.py
loadingpy-0.1.4.dist-info/METADATA
loadingpy-0.1.4.dist-info/WHEEL
loadingpy-0.1.4.dist-info/RECORD
